ssh_proto_types/__init__.py
ssh_proto_types/basetypes.py
ssh_proto_types/packet.py
ssh_proto_types/py.typed
ssh_proto_types/stream.py
ssh_proto_types-0.1.17.dist-info/METADATA
ssh_proto_types-0.1.17.dist-info/WHEEL
ssh_proto_types-0.1.17.dist-info/licenses/LICENSE
ssh_proto_types-0.1.17.dist-info/RECORD
