Metadata-Version: 2.4
Name: ssh-proto-types
Version: 0.1.17
Summary: Parser of SSH Protocol types
Project-URL: Homepage, https://github.com/KalleDK/py-ssh-proto-types
Project-URL: Documentation, https://github.com/KalleDK/py-ssh-proto-types
Project-URL: Repository, https://github.com/KalleDK/py-ssh-proto-types.git
Author-email: "Kalle M. Krog Aagaard" <git@k-moeller.dk>
Maintainer-email: "Kalle M. Krog Aagaard" <git@k-moeller.dk>
License-File: LICENSE
Classifier: License :: OSI Approved :: MIT License
Classifier: Programming Language :: Python :: 3.13
Requires-Python: >=3.13
